rss_for_free/__init__.py
rss_for_free/__main__.py
rss_for_free/settings.py
rss_for_free/sites/__init__.py
rss_for_free/sites/mt.py
rss_for_free/sites/nanyang.py
rss_for_free/utils/__init__.py
rss_for_free/utils/pt_rss.py
rss_for_free/utils/rss_for_free.py
rss_for_free/utils/set_config.py
rss_for_free-1.1.dist-info/METADATA
rss_for_free-1.1.dist-info/WHEEL
rss_for_free-1.1.dist-info/entry_points.txt
rss_for_free-1.1.dist-info/top_level.txt
rss_for_free-1.1.dist-info/RECORD
