Metadata-Version: 2.1
Name: rss-for-free
Version: 1.1
Summary: This is a script of pt
Home-page: UNKNOWN
Author: mxdie
Author-email: leurd@qq.com
License: UNKNOWN
Platform: UNKNOWN
Requires-Python: >=3
